goodorfs/__init__.py
goodorfs/classify.py
goodorfs/features.py
goodorfs/file_handling.py
goodorfs/functions.py
goodorfs/orf.py
goodorfs-1.0.data/scripts/goodorfs.py
goodorfs-1.0.dist-info/LICENSE
goodorfs-1.0.dist-info/METADATA
goodorfs-1.0.dist-info/WHEEL
goodorfs-1.0.dist-info/top_level.txt
goodorfs-1.0.dist-info/RECORD
