Metadata-Version: 2.1
Name: goodorfs
Version: 1.0
Summary: A a tool to find coding orfs
Home-page: https://github.com/deprekate/goodorfs
Author: Katelyn McNair
Author-email: deprekate@gmail.com
License: UNKNOWN
Platform: UNKNOWN
Classifier: Programming Language :: Python :: 3
Classifier: License :: OSI Approved :: GNU General Public License v3 or later (GPLv3+)
Classifier: Operating System :: OS Independent
Requires-Python: >3.5.2
Requires-Dist: sklearn
Requires-Dist: numpy
